temblor/__init__.py
temblor-0.1.0.dist-info/METADATA
temblor-0.1.0.dist-info/WHEEL
temblor-0.1.0.dist-info/top_level.txt
temblor-0.1.0.dist-info/RECORD
