Metadata-Version: 2.1
Name: temblor
Version: 0.1.0
Summary: Libraries to use Temblor services
Author-email: "Temblor, Inc Dev Team" <help@temblor.net>
Project-URL: Homepage, https://temblor.net
Requires-Python: >=3.7
